MANIFEST.in
README.rst
setup.py
django_oscar_paymentexpress.egg-info/PKG-INFO
django_oscar_paymentexpress.egg-info/SOURCES.txt
django_oscar_paymentexpress.egg-info/dependency_links.txt
django_oscar_paymentexpress.egg-info/requires.txt
django_oscar_paymentexpress.egg-info/top_level.txt
paymentexpress/__init__.py
paymentexpress/facade.py
paymentexpress/gateway.py
paymentexpress/models.py
paymentexpress/migrations/0001_initial.py
paymentexpress/migrations/__init__.py