Metadata-Version: 1.1
Name: django-oscar-paymentexpress
Version: 0.1.1
Summary: PaymentExpress payment module for django-oscar
Home-page: https://github.com/tangentlabs/django-oscar-paymentexpress
Author: Francis Reyes
Author-email: francis.reyes@tangentsnowball.com.au
License: BSD
Keywords: Payment,PaymentExpress
Platform: UNKNOWN
Classifier: Environment :: Web Environment
Classifier: Framework :: Django
Classifier: Intended Audience :: Developers
Classifier: License :: OSI Approved :: BSD License
Classifier: Operating System :: OS Independent
Classifier: Programming Language :: Python
